sleento/__init__.py
sleento/service.py
tests/__init__.py
tests/test_service.py
sleento-0.0.3.dist-info/METADATA
sleento-0.0.3.dist-info/WHEEL
sleento-0.0.3.dist-info/top_level.txt
sleento-0.0.3.dist-info/RECORD
