Metadata-Version: 2.1
Name: sleento
Version: 0.0.3
Summary: SleentO Python package for sending sms to your customer
Home-page: https://github.com/sleento/sleento-python
Author: Ged-flod
Author-email: magenta.sleento@gmail.com
License: MIT
Keywords: sleento,sleento-python,sleento-code
Platform: UNKNOWN
Requires-Python: >=3.6
Requires-Dist: requests (>=2.22.0)
